shopping_cart_387dd67aa803/__init__.py
shopping_cart_387dd67aa803/shopping_cart.py
shopping_cart_387dd67aa803/utils/__init__.py
shopping_cart_387dd67aa803/utils/utilities.py
shopping_cart_387dd67aa803-0.2.0.dist-info/METADATA
shopping_cart_387dd67aa803-0.2.0.dist-info/WHEEL
shopping_cart_387dd67aa803-0.2.0.dist-info/RECORD
