Metadata-Version: 2.1
Name: shopping-cart-387dd67aa803
Version: 0.2.0
Summary: Simple shopping cart that lets you add items and display the state of the cart
Author: None
Requires-Python: >=3.10,<4.0
Classifier: Programming Language :: Python :: 3
Classifier: Programming Language :: Python :: 3.10
Classifier: Programming Language :: Python :: 3.11
Classifier: Programming Language :: Python :: 3.12
Requires-Dist: requests (>=2.31.0,<3.0.0)
